README.txt
setup.py
quickmysql/__init__.py
quickmysql/quickmysql.py
quickmysql/try.py
quickmysql.egg-info/PKG-INFO
quickmysql.egg-info/SOURCES.txt
quickmysql.egg-info/dependency_links.txt
quickmysql.egg-info/not-zip-safe
quickmysql.egg-info/requires.txt
quickmysql.egg-info/top_level.txt