Metadata-Version: 1.1
Name: quickmysql
Version: 0.23
Summary: a tool to simplify common mysql tasks
Home-page: http://example.com
Author: Banio Carpenter
Author-email: banio@mncarpenters.net
License: BSD
Platform: UNKNOWN
Classifier: Development Status :: 3 - Alpha
Classifier: Environment :: Web Environment
Classifier: Intended Audience :: Developers
Classifier: License :: OSI Approved :: BSD License
Classifier: Operating System :: OS Independent
Classifier: Programming Language :: Python :: 3.5
